appkit_imagecreator/__init__.py
appkit_imagecreator/configuration.py
appkit_imagecreator/pages.py
appkit_imagecreator/state.py
appkit_imagecreator/backend/generator_registry.py
appkit_imagecreator/backend/image_api.py
appkit_imagecreator/backend/models.py
appkit_imagecreator/backend/repository.py
appkit_imagecreator/backend/generators/__init__.py
appkit_imagecreator/backend/generators/black_forest_labs.py
appkit_imagecreator/backend/generators/google.py
appkit_imagecreator/backend/generators/nano_banana.py
appkit_imagecreator/backend/generators/openai.py
appkit_imagecreator/components/count.py
appkit_imagecreator/components/history.py
appkit_imagecreator/components/image_props.py
appkit_imagecreator/components/images.py
appkit_imagecreator/components/keyboard_handler.py
appkit_imagecreator/components/prompt.py
appkit_imagecreator/components/styles.py
appkit_imagecreator-1.0.1.dist-info/METADATA
appkit_imagecreator-1.0.1.dist-info/WHEEL
appkit_imagecreator-1.0.1.dist-info/RECORD
